nameko_prometheus/__init__.py
nameko_prometheus/dependencies.py
nameko_prometheus/py.typed
nameko_prometheus/utils.py
nameko_prometheus-1.6.0.dist-info/AUTHORS.rst
nameko_prometheus-1.6.0.dist-info/LICENSE
nameko_prometheus-1.6.0.dist-info/METADATA
nameko_prometheus-1.6.0.dist-info/WHEEL
nameko_prometheus-1.6.0.dist-info/top_level.txt
nameko_prometheus-1.6.0.dist-info/RECORD
