Metadata-Version: 2.1
Name: nameko-prometheus
Version: 1.6.0
Summary: nameko-prometheus is a dependency for the nameko microservice framework which allows application metrics collection with Prometheus.
Author: Emplocity
License: Apache Software License 2.0
Project-URL: Homepage, https://github.com/emplocity/nameko-prometheus
Project-URL: Documentation, https://nameko-prometheus.readthedocs.io/
Project-URL: Changelog, https://nameko-prometheus.readthedocs.io/en/latest/changelog.html
Project-URL: Issue Tracker, https://github.com/emplocity/nameko-prometheus/issues
Classifier: Development Status :: 3 - Alpha
Classifier: Intended Audience :: Developers
Classifier: License :: OSI Approved :: Apache Software License
Classifier: Operating System :: Unix
Classifier: Operating System :: POSIX
Classifier: Programming Language :: Python
Classifier: Programming Language :: Python :: 3
Classifier: Programming Language :: Python :: 3.8
Classifier: Programming Language :: Python :: 3.9
Classifier: Programming Language :: Python :: 3.10
Classifier: Programming Language :: Python :: Implementation :: CPython
Classifier: Topic :: Utilities
Requires-Python: >=3.8
License-File: LICENSE
License-File: AUTHORS.rst
Requires-Dist: nameko <4,>=2
Requires-Dist: prometheus-client <1,>=0.15
